primegenerators/__init__.py
primegenerators/__main__.py
primegenerators/algorithms.py
primegenerators/generators/__init__.py
primegenerators/generators/eratosthenes_generator.py
primegenerators/generators/factory.py
primegenerators/generators/prime_generator.py
primegenerators-0.0.11.dist-info/METADATA
primegenerators-0.0.11.dist-info/WHEEL
primegenerators-0.0.11.dist-info/RECORD
