Metadata-Version: 2.1
Name: primegenerators
Version: 0.0.11
Summary: A library of prime number generators and analyzers, that also has a command-line interface
License: Apache-2.0
Keywords: prime,numbers,generator,cli
Author: big-jr
Author-email: githubcomms@softwarepragmatism.com
Requires-Python: >=3.12,<4.0
Classifier: Development Status :: 4 - Beta
Classifier: Environment :: Console
Classifier: License :: OSI Approved :: Apache Software License
Classifier: Operating System :: OS Independent
Classifier: Programming Language :: Python :: 3
Classifier: Programming Language :: Python :: 3.12
Classifier: Programming Language :: Python :: 3.13
Classifier: Topic :: Software Development :: Libraries
